social_media_fetch/Data_access_layer.py
social_media_fetch/__init__.py
social_media_fetch/data_collection.py
social_media_fetch/update_dataset.py
social_media_fetch/user_interface.py
social_media_fetch-0.0.1.dist-info/LICENSE
social_media_fetch-0.0.1.dist-info/METADATA
social_media_fetch-0.0.1.dist-info/WHEEL
social_media_fetch-0.0.1.dist-info/top_level.txt
social_media_fetch-0.0.1.dist-info/RECORD
