Metadata-Version: 2.1
Name: social-media-fetch
Version: 0.0.1
Summary: Read My social Media for me !
Author-email: Neha Verma <v005neha@gmail.com>
Keywords: Mastodon,Sentiment Analysis,Fetch Post
Classifier: Programming Language :: Python :: 3
Classifier: License :: OSI Approved :: MIT License
Classifier: Operating System :: OS Independent
Requires-Python: >=3.7
License-File: LICENSE
Requires-Dist: tkinter
Requires-Dist: mastodon
Requires-Dist: csv
